ipcheck/__init__.py
ipcheck/config-ex.ini
ipcheck/geo-ex.ini
ipcheck/geoinfo.py
ipcheck/main.py
ipcheck/app/__init__.py
ipcheck/app/base_config.py
ipcheck/app/common_config.py
ipcheck/app/config.py
ipcheck/app/gen_ip_utils.py
ipcheck/app/geo_utils.py
ipcheck/app/ip_info.py
ipcheck/app/ip_parser.py
ipcheck/app/rtt_test.py
ipcheck/app/rtt_test_config.py
ipcheck/app/speed_test.py
ipcheck/app/speed_test_config.py
ipcheck/app/statemachine.py
ipcheck/app/utils.py
ipcheck/app/valid_test.py
ipcheck/app/valid_test_config.py
ip_check-2.3.5.dist-info/LICENSE
ip_check-2.3.5.dist-info/METADATA
ip_check-2.3.5.dist-info/WHEEL
ip_check-2.3.5.dist-info/entry_points.txt
ip_check-2.3.5.dist-info/top_level.txt
ip_check-2.3.5.dist-info/RECORD
