Metadata-Version: 2.1
Name: ip-check
Version: 2.3.5
Summary: Powerful cdn network speed test utils.
Author: nobitaqaq
Author-email: xiaoleigs@gmail.com
Keywords: cdn,speed test,network speed
Requires-Python: >=3.8
License-File: LICENSE
Requires-Dist: geoip2
Requires-Dist: ipaddress
Requires-Dist: requests
Requires-Dist: requests[socks]
Requires-Dist: tqdm
Requires-Dist: urllib3 >=2.2.3
Requires-Dist: importlib-metadata
